jenova/__init__.py
jenova/api.py
jenova/middleware.py
jenova/response.py
jenova-0.1.0.dist-info/LICENSE
jenova-0.1.0.dist-info/WHEEL
jenova-0.1.0.dist-info/METADATA
jenova-0.1.0.dist-info/RECORD
