Metadata-Version: 2.1
Name: jenova
Version: 0.1.0
Summary: Web framework built for learning purpose
Author: Tobi-De
Author-email: tobidegnon@protonmail.com
Requires-Python: >=3.10,<4.0
Classifier: Programming Language :: Python :: 3
Classifier: Programming Language :: Python :: 3.10
Requires-Dist: Jinja2 (>=3.1.2,<4.0.0)
Requires-Dist: WebOb (>=1.8.7,<2.0.0)
Requires-Dist: gunicorn (>=20.1.0,<21.0.0)
Requires-Dist: httpx (>=0.23.0,<0.24.0)
Requires-Dist: parse (>=1.19.0,<2.0.0)
Requires-Dist: requests (>=2.27.1,<3.0.0)
Requires-Dist: requests-wsgi-adapter (>=0.4.1,<0.5.0)
Requires-Dist: whitenoise (>=6.2.0,<7.0.0)
